MANIFEST.in
README.md
quicktest.py
settings_test.py
setup.py
django_facebook_api.egg-info/PKG-INFO
django_facebook_api.egg-info/SOURCES.txt
django_facebook_api.egg-info/dependency_links.txt
django_facebook_api.egg-info/not-zip-safe
django_facebook_api.egg-info/requires.txt
django_facebook_api.egg-info/top_level.txt
facebook_api/__init__.py
facebook_api/__init__.pyc
facebook_api/admin.py
facebook_api/admin.pyc
facebook_api/api.py
facebook_api/api.pyc
facebook_api/decorators.py
facebook_api/decorators.pyc
facebook_api/fields.py
facebook_api/fields.pyc
facebook_api/mixins.py
facebook_api/mixins.pyc
facebook_api/models.py
facebook_api/models.pyc
facebook_api/parser.py
facebook_api/parser.pyc
facebook_api/signals.py
facebook_api/signals.pyc
facebook_api/tests.py
facebook_api/tests.pyc
facebook_api/utils.py
facebook_api/utils.pyc